{
	"format_version": "1.8.0",
	"animations": {
		"idle": {
			"loop": true,
			"animation_length": 1,
			"bones": {
				"nose": {
					"rotation": {
						"0.0": {
							"vector": [-12.5, 0, 0]
						},
						"0.5": {
							"vector": [7.5, 0, 0],
							"easing": "easeOutElastic"
						},
						"1.0": {
							"vector": [-12.5, 0, 0],
							"easing": "easeOutElastic"
						}
					}
				},
				"up": {
					"rotation": {
						"0.0": {
							"vector": [-25, 0, 0]
						},
						"0.5": {
							"vector": [20, 0, 0],
							"easing": "easeInElastic"
						},
						"1.0": {
							"vector": [-25, 0, 0],
							"easing": "easeInElastic"
						}
					}
				},
				"brow": {
					"position": {
						"0.375": {
							"vector": [0, 0, 0]
						},
						"0.5": {
							"vector": [0, -1, 0]
						},
						"0.625": {
							"vector": [0, 0, 0]
						}
					}
				},
				"brow2": {
					"position": {
						"0.375": {
							"vector": [0, 0, 0]
						},
						"0.5": {
							"vector": [0, -1, 0]
						},
						"0.625": {
							"vector": [0, 0, 0]
						}
					}
				},
				"arm": {
					"rotation": {
						"0.0": {
							"vector": [42.5, 0, -10]
						},
						"0.5": {
							"vector": [17.5, 0, -22.5],
							"easing": "easeOutElastic"
						},
						"1.0": {
							"vector": [42.5, 0, -10],
							"easing": "easeOutElastic"
						}
					}
				},
				"arm2": {
					"rotation": {
						"0.0": {
							"vector": [-137.5, 0, 0]
						},
						"0.5": {
							"vector": [-27.5, 0, 0],
							"easing": "easeInElastic"
						},
						"1.0": {
							"vector": [-137.5, 0, 0],
							"easing": "easeInElastic"
						}
					}
				},
				"glasses": {
					"rotation": {
						"0.0": {
							"vector": [-15, 0, 0]
						},
						"0.5": {
							"vector": [15, 0, 0],
							"easing": "easeOutElastic"
						},
						"1.0": {
							"vector": [-15, 0, 0],
							"easing": "easeOutElastic"
						}
					}
				}
			}
		}
	}
}